{
"propiedadesCertificadoSalida":[
{
"A":"05197043D",
"B":"CLEMENTE RODRIGUEZ MARIA BEGOÑA",
"C":"439405A14CA62C7664D3B3455549462F",
"D":"09/08/2023",
"E":"09/08/2026",
"F":"",
"G":"",
"H":"CLEMENTE RODRIGUEZ MARIA BEGOÑA - 05197043D",
"I":"E822C25455483336DD7B0A61E4311E6113ECDF99",
"J":""
},
{
"A":"X8013621F",
"B":"SEUCEA VERONICA",
"C":"38463E32BD1BA1C663E381BB570BCBBE",
"D":"08/02/2023",
"E":"08/02/2027",
"F":"",
"G":"",
"H":"SEUCEA VERONICA - X8013621F",
"I":"D9CB8A6A24AB51D64857162307AE895D33081AFE",
"J":""
},
{
"A":"04870614L",
"B":"RODRIGUEZ SANCHEZ AMPARO",
"C":"36752A3651E9069A66E14EC12C68C1F4",
"D":"11/09/2024",
"E":"11/09/2028",
"F":"",
"G":"",
"H":"RODRIGUEZ SANCHEZ AMPARO - 04870614L",
"I":"D339A40073DBC8224E783AB1080AED9282964FAE",
"J":""
},
{
"A":"G02114650",
"B":"CASA DE ARAGON EN ALBACETE",
"C":"693B06A642E7CCB36756BD0C475A3E5B",
"D":"09/12/2024",
"E":"09/12/2026",
"F":"17699412S",
"G":"LAMBEA BAILO JESUS",
"H":"17699412S JESUS LAMBEA (R:G02114650)",
"I":"C88C645E7484C2EC26F6578169D8D81AD55BCAC5",
"J":""
},
{
"A":"55493910Q",
"B":"SEUCEA BARNA FLORINA IULIA",
"C":"320951F5DA9C9AA6621CA7F7ABDACF92",
"D":"28/02/2022",
"E":"28/02/2026",
"F":"",
"G":"",
"H":"SEUCEA BARNA FLORINA IULIA - 55493910Q",
"I":"BFFD4EFCE8E6E53CB09B85D577DBCD26D07B82C2",
"J":""
},
{
"A":"05165277Y",
"B":"CLEMENTE RODRIGUEZ ANA MARIA",
"C":"2B24373EFD77A9F3677FA18F07E7E6B5",
"D":"09/01/2025",
"E":"09/01/2029",
"F":"",
"G":"",
"H":"CLEMENTE RODRIGUEZ ANA MARIA - 05165277Y",
"I":"BD8CE26D6EA68CD12923BD3CD9791F2F8EC6C2BE",
"J":""
},
{
"A":"47090504M",
"B":"CLEMENTE NARANJO LUIS",
"C":"7903EA0406844CBF67713581FB23B476",
"D":"29/12/2024",
"E":"29/12/2028",
"F":"",
"G":"",
"H":"CLEMENTE NARANJO LUIS - 47090504M",
"I":"9E5D6FE087F0DF6752715BC352D51C97C3C10F2A",
"J":""
},
{
"A":"24156644C",
"B":"MARTINEZ PORTILLO RAMON",
"C":"616E13FD671D1B326440520E828DAC57",
"D":"19/04/2023",
"E":"19/04/2027",
"F":"",
"G":"",
"H":"MARTINEZ PORTILLO RAMON - 24156644C",
"I":"8FD1D89A23D7866F3BED99A61E08139F8E10D3F8",
"J":""
},
{
"A":"05126963X",
"B":"NARANJO RUIZ MARIA JOSEFA",
"C":"6905F837AFA8C48261288E3C536FC951",
"D":"27/08/2021",
"E":"27/08/2025",
"F":"",
"G":"",
"H":"NARANJO RUIZ MARIA JOSEFA - 05126963X",
"I":"8B25B0D04E9BCA8B8D50D84247B4E1486C574F8F",
"J":""
},
{
"A":"05196375P",
"B":"CLEMENTE RODRIGUEZ CARLOS ENRIQUE",
"C":"581C0656167D9349677E3EB0A45BE8BD",
"D":"08/01/2025",
"E":"08/01/2029",
"F":"",
"G":"",
"H":"CLEMENTE RODRIGUEZ CARLOS ENRIQUE - 05196375P",
"I":"63D068801DB0CC47B414D1D8B6F6EEF1716F8E67",
"J":""
},
{
"A":"B02219319",
"B":"SPITZER ENTERPRISES SOCIEDAD LIMITADA",
"C":"377889D95E79F7C167D887BD36D5DF5C",
"D":"17/03/2025",
"E":"17/03/2027",
"F":"51055744E",
"G":"SPITZER YSBERT JOSE",
"H":"51055744E JOSE SPITZER (R:B02219319)",
"I":"41EDD19BD45D54C128E46C3FD0FE91CCD4D75C6B",
"J":""
},
{
"A":"51055744E",
"B":"SPITZER YSBERT JOSE",
"C":"5AF89F5056EAB8EA67D7E6303829EAB0",
"D":"17/03/2025",
"E":"17/03/2029",
"F":"",
"G":"",
"H":"SPITZER YSBERT JOSE - 51055744E",
"I":"3F55B431E1233C1657F4DEE2D04357AEAAB6A823",
"J":""
},
{
"A":"17244524K",
"B":"CLEMENTE SORIA ANA",
"C":"66C496323D027F44651E6C67DAD3A16C",
"D":"05/10/2023",
"E":"05/10/2027",
"F":"",
"G":"",
"H":"CLEMENTE SORIA ANA - 17244524K",
"I":"36114682E232C8FF18F7D206A8F110C16D9F36EC",
"J":""
},
{
"A":"44382709T",
"B":"TEVAR GARCIA MARIA ISABEL",
"C":"4D483E9F0BFE7BDD67288DAFF1EAA2F8",
"D":"04/11/2024",
"E":"04/11/2028",
"F":"",
"G":"",
"H":"TEVAR GARCIA MARIA ISABEL - 44382709T",
"I":"32F160A586BA8687A6A8A626F62871EC092606A1",
"J":""
},
{
"A":"05055063P",
"B":"RODRIGUEZ SANCHEZ JOSE MARIA",
"C":"67DDB7331B38F2D066E14F2CD262C368",
"D":"11/09/2024",
"E":"11/09/2028",
"F":"",
"G":"",
"H":"RODRIGUEZ SANCHEZ JOSE MARIA - 05055063P",
"I":"2AF939A7EC7166946166FAC97A28C178762B6572",
"J":""
},
{
"A":"48152922F",
"B":"CLEMENTE NARANJO CRISTINA",
"C":"3516BF47815C6B0C65FD3D76A2F9E6B7",
"D":"22/03/2024",
"E":"22/03/2028",
"F":"",
"G":"",
"H":"CLEMENTE NARANJO CRISTINA - 48152922F",
"I":"26D6F15EC70E48909DD43048BD073CB774162E8D",
"J":""
}
]
}